renumnum/__init__.py
renumnum/beads_notation.py
renumnum/dictionary_order_number.py
renumnum-0.2.2.dist-info/METADATA
renumnum-0.2.2.dist-info/WHEEL
renumnum-0.2.2.dist-info/licenses/LICENSE
renumnum-0.2.2.dist-info/RECORD
