Metadata-Version: 2.3
Name: renumnum
Version: 0.2.2
Summary: Numbering notation for easy renumbering.
Project-URL: Repository, https://github.com/muzudho/renumberingist-number.git
Author-email: "Takahashi Satoshi (Handle Name:むずでょ)" <muzudho1@gmail.com>
Maintainer-email: "Takahashi Satoshi (Handle Name:むずでょ)" <muzudho1@gmail.com>
License: MIT License
License-File: LICENSE
Keywords: notation,renumbering
Classifier: Programming Language :: Python
